tests/__init__.py
tests/test_simple.py
tsclust/__init__.py
tsclust/example.py
tsclust/stepattern.py
tsclust-0.1.0.dist-info/AUTHORS.rst
tsclust-0.1.0.dist-info/LICENSE
tsclust-0.1.0.dist-info/METADATA
tsclust-0.1.0.dist-info/WHEEL
tsclust-0.1.0.dist-info/entry_points.txt
tsclust-0.1.0.dist-info/top_level.txt
tsclust-0.1.0.dist-info/RECORD
