Metadata-Version: 2.1
Name: tsclust
Version: 0.1.0
Summary: Streaming Time-series Clustering
Home-page: https://github.com/imartinezl/tsclust
Author: Iñigo Martinez
Author-email: inigomlap@gmail.com
License: MIT license
Project-URL: Bug Reports, https://github.com/imartinezl/tsclust/issues
Project-URL: Documentation, https://tslearn.readthedocs.io
Project-URL: Source Code, https://github.com/imartinezl/tsclust
Keywords: time series,clustering,streaming,average
Platform: UNKNOWN
Classifier: Development Status :: 2 - Pre-Alpha
Classifier: Intended Audience :: Developers
Classifier: License :: OSI Approved :: MIT License
Classifier: Natural Language :: English
Classifier: Programming Language :: Python :: 3
Classifier: Programming Language :: Python :: 3.5
Classifier: Programming Language :: Python :: 3.6
Classifier: Programming Language :: Python :: 3.7
Classifier: Programming Language :: Python :: 3.8
Requires-Python: >=3.5, <4
Requires-Dist: numpy
Requires-Dist: numba
Requires-Dist: matplotlib
Requires-Dist: tabulate
